{
  "name": "Booking.com",
  "description": "World's leading online travel agency and accommodation booking platform, offering millions of properties worldwide including hotels, apartments, vacation rentals, and more. Part of Booking Holdings Inc., providing travelers with comprehensive booking services, reviews, and travel deals across the globe.",
  "country": "Netherlands",
  "founded": "1996",
  "tags": [
    "Travel Tech & Platforms"
  ],
  "website": "https://www.booking.com/",
  "added": "2025-11-10",
  "lastModified": "2025-11-10"
}

